screenpy/__init__.py
screenpy/__version__.py
screenpy/actions/__init__.py
screenpy/actions/attach_the_file.py
screenpy/actions/debug.py
screenpy/actions/either.py
screenpy/actions/eventually.py
screenpy/actions/log.py
screenpy/actions/make_note.py
screenpy/actions/pause.py
screenpy/actions/see.py
screenpy/actions/see_all_of.py
screenpy/actions/see_any_of.py
screenpy/actions/silently.py
screenpy/actions/stop.py
screenpy/actor.py
screenpy/configuration.py
screenpy/directions.py
screenpy/director.py
screenpy/exceptions.py
screenpy/given_when_then.py
screenpy/narration/__init__.py
screenpy/narration/gravitas.py
screenpy/narration/narrator.py
screenpy/narration/stdout_adapter/__init__.py
screenpy/narration/stdout_adapter/configuration.py
screenpy/narration/stdout_adapter/stdout_adapter.py
screenpy/pacing.py
screenpy/protocols.py
screenpy/py.typed
screenpy/resolutions/__init__.py
screenpy/resolutions/base_resolution.py
screenpy/resolutions/contains_item_matching.py
screenpy/resolutions/contains_the_entry.py
screenpy/resolutions/contains_the_item.py
screenpy/resolutions/contains_the_key.py
screenpy/resolutions/contains_the_text.py
screenpy/resolutions/contains_the_value.py
screenpy/resolutions/custom_matchers/__init__.py
screenpy/resolutions/custom_matchers/is_in_bounds.py
screenpy/resolutions/custom_matchers/sequence_containing_pattern.py
screenpy/resolutions/ends_with.py
screenpy/resolutions/has_length.py
screenpy/resolutions/is_close_to.py
screenpy/resolutions/is_empty.py
screenpy/resolutions/is_equal_to.py
screenpy/resolutions/is_greater_than.py
screenpy/resolutions/is_greater_than_or_equal_to.py
screenpy/resolutions/is_in_range.py
screenpy/resolutions/is_less_than.py
screenpy/resolutions/is_less_than_or_equal_to.py
screenpy/resolutions/is_not.py
screenpy/resolutions/matches.py
screenpy/resolutions/reads_exactly.py
screenpy/resolutions/starts_with.py
screenpy/speech_tools.py
screenpy-5.0.0.dist-info/METADATA
screenpy-5.0.0.dist-info/WHEEL
screenpy-5.0.0.dist-info/licenses/LICENSE
screenpy-5.0.0.dist-info/RECORD
