Metadata-Version: 2.4
Name: screenpy
Version: 5.0.0
Summary: Screenplay pattern base for Python automated test suites.
License: MIT
License-File: LICENSE
Author: Perry Goy
Author-email: perry.goy@gmail.com
Maintainer: Gabe Langton
Requires-Python: >=3.9,<4.0
Classifier: Development Status :: 5 - Production/Stable
Classifier: Intended Audience :: Developers
Classifier: License :: OSI Approved :: MIT License
Classifier: Natural Language :: English
Classifier: Operating System :: OS Independent
Classifier: Programming Language :: Python :: 3
Classifier: Programming Language :: Python :: 3.9
Classifier: Programming Language :: Python :: 3.10
Classifier: Programming Language :: Python :: 3.11
Classifier: Programming Language :: Python :: 3.12
Classifier: Programming Language :: Python :: 3.13
Classifier: Programming Language :: Python :: 3.14
Classifier: Programming Language :: Python :: 3 :: Only
Classifier: Topic :: Software Development :: Quality Assurance
Classifier: Topic :: Software Development :: Testing
Classifier: Topic :: Software Development :: Testing :: BDD
Provides-Extra: allure
Provides-Extra: appium
Provides-Extra: dev
Provides-Extra: docs
Provides-Extra: playwright
Provides-Extra: pyotp
Provides-Extra: requests
Provides-Extra: selenium
Provides-Extra: test
Requires-Dist: PyHamcrest (>=2.0.0)
Requires-Dist: autodoc-pydantic ; extra == "dev" or extra == "docs"
Requires-Dist: black ; extra == "dev"
Requires-Dist: coverage ; extra == "dev" or extra == "test"
Requires-Dist: cruft ; extra == "dev"
Requires-Dist: importlib_metadata ; python_version == "3.9"
Requires-Dist: mypy ; extra == "dev"
Requires-Dist: pre-commit ; extra == "dev"
Requires-Dist: pydantic
Requires-Dist: pydantic-settings
Requires-Dist: pytest ; extra == "dev" or extra == "test"
Requires-Dist: pytest-mock ; extra == "dev" or extra == "test"
Requires-Dist: ruff (>=0.2.0) ; extra == "dev"
Requires-Dist: screenpy-adapter_allure (>=4.0.1,<5.0.0) ; extra == "allure"
Requires-Dist: screenpy-appium ; extra == "appium"
Requires-Dist: screenpy-playwright ; extra == "playwright"
Requires-Dist: screenpy-pyotp (>=4.0.1,<5.0.0) ; extra == "pyotp"
Requires-Dist: screenpy-requests (>=4.0.1,<5.0.0) ; extra == "requests"
Requires-Dist: screenpy-selenium (>=4.0.3,<5.0.0) ; extra == "selenium"
Requires-Dist: sphinx ; extra == "dev" or extra == "docs"
Requires-Dist: sphinx-rtd-theme ; extra == "dev" or extra == "docs"
Requires-Dist: tomli (>=2.0.1) ; python_version < "3.11"
Requires-Dist: tox ; extra == "dev"
Requires-Dist: typing_extensions (>=4.8.0)
Project-URL: Documentation, https://screenpy-docs.readthedocs.io
Project-URL: Repository, https://github.com/ScreenPyHQ/screenpy
